trajectory/__init__.py
trajectory/codec.py
trajectory-0.1.1.dist-info/LICENSE
trajectory-0.1.1.dist-info/WHEEL
trajectory-0.1.1.dist-info/METADATA
trajectory-0.1.1.dist-info/RECORD
