Metadata-Version: 2.1
Name: trajectory
Version: 0.1.1
Summary: Trajectory data lossy compression format based on Google's Encoded Polyline Algorithm Format
Home-page: https://github.com/adonmo/trajectory
License: MIT
Keywords: geo,gis,postgres,mobility,trajectory,spatiotemporal
Author: B Krishna Chaitanya
Author-email: bkchaitan94@gmail.com
Requires-Python: >=3.6
Classifier: Development Status :: 3 - Alpha
Classifier: Environment :: Plugins
Classifier: Intended Audience :: Developers
Classifier: Intended Audience :: Information Technology
Classifier: Intended Audience :: Science/Research
Classifier: License :: OSI Approved :: MIT License
Classifier: Natural Language :: English
Classifier: Operating System :: OS Independent
Classifier: Programming Language :: Python
Classifier: Programming Language :: Python :: 3
Classifier: Programming Language :: Python :: 3.6
Classifier: Programming Language :: Python :: 3.7
Classifier: Programming Language :: Python :: 3.8
Classifier: Topic :: Database :: Database Engines/Servers
Classifier: Topic :: Scientific/Engineering :: GIS
Requires-Dist: six (>=1.14.0,<2.0.0)
Project-URL: Documentation, https://github.com/adonmo/trajectory
Project-URL: Repository, https://github.com/adonmo/trajectory
